pandect/__init__.py
pandect/pandect.py
pandect-0.4.0.dist-info/entry_points.txt
pandect-0.4.0.dist-info/LICENSE
pandect-0.4.0.dist-info/WHEEL
pandect-0.4.0.dist-info/METADATA
pandect-0.4.0.dist-info/RECORD
