Metadata-Version: 2.1
Name: pandect
Version: 0.4.0
Summary: Simple wrappers to load and convert common data file types
Home-page: https://github.com/datagazing/pandect
Author: Brendan Strejcek
Author-email: brendan@datagazing.com
Requires-Python: >=3.7
Classifier: License :: OSI Approved :: MIT License
Requires-Dist: optini
Requires-Dist: pandas
Requires-Dist: pyreadstat
Requires-Dist: openpyxl
